README.md
licence.txt
setup.py
Pro_Car_Automation.egg-info/PKG-INFO
Pro_Car_Automation.egg-info/SOURCES.txt
Pro_Car_Automation.egg-info/dependency_links.txt
Pro_Car_Automation.egg-info/top_level.txt
Pro_Car_Tools/__init__.py
Pro_Car_Tools/car_automation.py
Pro_Car_Tools/ship_automation.py