Metadata-Version: 2.1
Name: Pro-Car-Automation
Version: 1.0
Summary: este pacote irá fornecer ferramentas de automação para veículos
Author: Estevao Ramos
Author-email: estevao.sr@live.com
Keywords: carro,automation,processamento
License-File: licence.txt
